[

{
    "imgsrc": "https://media.bakingo.com/sq-tasty-chocolate-truffle-past0162choc-A_0.jpg?tr=w-320,h-320,q-70",
    "title": " Chocolate Truffle Pastry",
    "indication": "This pastry is all about perfection, made from the finest quality of chocolate.",
    "dosage": "",
    "sideEffects": "",
    "price": 189,

"countInStock" : 50,      "category": "Women's Care"
},
{
    "imgsrc": "https://media.bakingo.com/sq-chocochips-oreo-jar-cake-jar249chocoreo-A_1.jpg",
    "title": " Chocochips And Oreo Jar Cake Combo",
    "indication": "This is the combo to perfect to gratify your senses. With an amazing combo of choco chip and Oreo",
    "dosage": "",
    "sideEffects": "",
    "price": 299,

"countInStock" : 50,      "category": "Women's Care"
},
{
    "imgsrc": "https://media.bakingo.com/sq-7E-Redvelvet-Jar-Cake-A_0.jpg?tr=w-320,h-320,q-70",
    "title": " Red Velvet Single Jar Cake",
    "indication": "Nothing matches to the goodness of a delectable red velvet jar cake",
    "dosage": "",
    "sideEffects": "",
    "price": 149,

"countInStock" : 50,      "category": "Women's Care"
},
{
    "imgsrc": "https://media.bakingo.com/sq-dry-cake-topped-with-berries-and-almonds-300gm-cake2459dryc-A.jpg?tr=w-320,h-320,q-70",
    "title": " Dry Cake Topped With Berries And Almonds (300gm)Shake",
    "indication": "The dry berry and almond cake is a purest delight to enjoy in your snack-time",
    "dosage": "",
    "sideEffects": "",
    "price": 279,

"countInStock" : 50,      "category": "Women's Care"
},
{
    "imgsrc": "https://media.bakingo.com/sq-overloaded-choco-cupcake-cupc0189choc-A_1.jpg",
    "title": " Choco Chip Cupcake",
    "indication": "If you wish for the taste of pure chocolaty delicacy, this cake could be an idea deal for you.",
    "dosage": "",
    "sideEffects": "",
    "price": 199,

"countInStock" : 50,      "category": "Women's Care"
},
{
    "imgsrc": "https://media.bakingo.com/sq-drool-worthy-chocolate-and-butterscotch-pateries-past2344flav-A_0.jpg?tr=w-320,h-320,q-70",
    "title": " Drool Worthy Chocolate",
    "indication": "Binge-eating fresh and delicious pastries in delightful flavours like Butterscotch and Chocolate",
    "dosage": "",
    "sideEffects": "",
    "price": 210,

"countInStock" : 50,      "category": "Women's Care"
},
{
    "imgsrc": "https://media.bakingo.com/sq-blueberry-jar-cakes-2-ml-with-red-velvet-cupcakes-jar2168redv-A_0.jpg",
    "title": "  Blueberry Jar Cakes",
    "indication": "Dig in the creamy and berrylicious layers of blueberry jar cake",
    "dosage": "",
    "sideEffects": "",
    "price": 549,

"countInStock" : 50,      "category": "Women's Care"
},
{
    "imgsrc": "https://mirchi.com/os/cdn/content/images/Sandwich%20Katli%20Jay%20Hind%20Sweets_medium819260.webp",
    "title": "  Sandwich Katli",
    "indication": "Pista barfi sandwiched with dry fruits like kaju and flavoured with saffron and cardamom.",
    "dosage": "",
    "sideEffects": "",
    "price": 460,

"countInStock" : 50,      "category": "Women's Care"
},
{
    "imgsrc": "https://mirchi.com/os/cdn/content/images/patisa%20tilkut%20gaya_medium_0799416.webp",
    "title": "Patisa",
    "indication": "A unique treat made from Sesame Seeds and Jaggery.",
    "dosage": "",
    "sideEffects": "",
    "price": 200,

"countInStock" : 50,      "category": "Women's Care"
},
{
    "imgsrc": "https://mirchi.com/os/cdn/content/images/Chocolate%20Mawa%20Burfi%20Punjabi%20Ghasitaram%20Halwai%20Pvt%20Ltd%20_medium926218.webp",
    "title": "  Mawa Chocolate Burfi",
    "indication": "Mawa Chocolate barfi is a traditional Indian Mithai or sweet dish with an added layer of Cocoa Powder with Mawa.",
    "dosage": "",
    "sideEffects": "",
    "price": 200,

"countInStock" : 50,      "category": "Women's Care"
},


{
    "imgsrc": "https://b.zmtcdn.com/data/pictures/4/19736834/ebabbbcafae49ce1caef42d9cdd3aa17.jpg?output-format=webp&fit=around|771.75:416.25&crop=771.75:416.25;*,*",
    "title": "  Rasgulla",
    "indication": "Rosogola is a South Asian syrupy dessert popular in the Indian subcontinent and regions with South Asian diaspora.",
    "dosage": "",
    "sideEffects": "",
    "price": 200,

"countInStock" : 50,      "category": "Women's Care"
},

{
    "imgsrc": "https://b.zmtcdn.com/data/pictures/6/19495046/511360534d8ac13d9d8db0937cada9d5.jpg?output-format=webp&fit=around|771.75:416.25&crop=771.75:416.25;*,*",
    "title": "  Gulab Jamun",
    "indication": "Gulab jamun are soft delicious berry sized balls made with milk solids, flour & a leavening agent.",
    "dosage": "",
    "sideEffects": "",
    "price": 200,

"countInStock" : 50,      "category": "Women's Care"
},

{
    "imgsrc": "https://mirchi.com/os/cdn/content/images/sugarfree%20kaju%20gujiya%20ghasitaram%20gifts_medium_0978428.webp",
    "title": "  Kaju Gujiya",
    "indication": "Shaped as a gujiya, made of finest quality cashew nuts topped with pistachio and enhanced",
    "dosage": "",
    "sideEffects": "",
    "price": 1099,

"countInStock" : 50,      "category": "Women's Care"
},

{
    "imgsrc": "https://mirchi.com/os/cdn/content/images/dry%20fruit%20badami%20halwa%20mm%20mithaiwala_medium_0867389.webp",
    "title": "  Badami Halwa",
    "indication": "Badam halwa is a rich, decadent, nutty South Indian style melt in the mouth ",
    "dosage": "",
    "sideEffects": "",
    "price": 600,

"countInStock" : 50,      "category": "Women's Care"
}








]